neuronnet/__init__.py
neuronnet/collective_learning.py
neuronnet/logger.py
neuronnet/model.py
neuronnet/test_collective_learning.py
neuronnet/training.py
neuronnet-0.4.1.dist-info/licenses/LICENCE
neuronnet-0.4.1.dist-info/METADATA
neuronnet-0.4.1.dist-info/WHEEL
neuronnet-0.4.1.dist-info/top_level.txt
neuronnet-0.4.1.dist-info/RECORD
