Metadata-Version: 2.4
Name: neuronnet
Version: 0.4.1
Summary: Библиотека для коллективного обучения нейросетей с использованием оптимизатора Adam, L2-регуляризации и мини-пакетов.
Home-page: https://github.com/yourusername/NeuronNet
Author: Umar
Author-email: umarfrost2011@gmail.com
License-File: LICENCE
Requires-Dist: numpy
Dynamic: author
Dynamic: author-email
Dynamic: description
Dynamic: description-content-type
Dynamic: home-page
Dynamic: license-file
Dynamic: requires-dist
Dynamic: summary
